{
 "_type": "song",
 "annotation_count": 1,
 "api_path": "/songs/1513892",
 "artist_names": "Johnny Preston",
 "full_title": "Running Bear by\u00a0Johnny\u00a0Preston",
 "header_image_thumbnail_url": "https://images.genius.com/bac016719ebf087d16d1752054ba62c6.300x300x1.jpg",
 "header_image_url": "https://images.genius.com/bac016719ebf087d16d1752054ba62c6.1000x1000x1.jpg",
 "id": 1513892,
 "instrumental": false,
 "lyrics_owner_id": 6261923,
 "lyrics_state": "complete",
 "lyrics_updated_at": 1658603949,
 "path": "/Johnny-preston-running-bear-lyrics",
 "pyongs_count": 1,
 "relationships_index_url": "https://genius.com/Johnny-preston-running-bear-sample",
 "release_date_components": {
  "year": 1959,
  "month": 8,
  "day": null
 },
 "release_date_for_display": "August 1959",
 "release_date_with_abbreviated_month_for_display": "Aug. 1959",
 "song_art_image_thumbnail_url": "https://images.genius.com/bac016719ebf087d16d1752054ba62c6.300x300x1.jpg",
 "song_art_image_url": "https://images.genius.com/bac016719ebf087d16d1752054ba62c6.1000x1000x1.jpg",
 "stats": {
  "unreviewed_annotations": 0,
  "hot": false,
  "pageviews": 15094
 },
 "title": "Running Bear",
 "title_with_featured": "Running Bear",
 "updated_by_human_at": 1668594934,
 "url": "https://genius.com/Johnny-preston-running-bear-lyrics",
 "featured_artists": [],
 "primary_artist": {
  "_type": "artist",
  "api_path": "/artists/370092",
  "header_image_url": "https://assets.genius.com/images/default_avatar_300.png?1699303299",
  "id": 370092,
  "image_url": "https://assets.genius.com/images/default_avatar_300.png?1699303299",
  "index_character": "j",
  "is_meme_verified": false,
  "is_verified": false,
  "name": "Johnny Preston",
  "slug": "Johnny-preston",
  "url": "https://genius.com/artists/Johnny-preston"
 },
 "artist": "Johnny Preston",
 "lyrics": "7 ContributorsRunning Bear Lyrics[Intro]\n*vocalizations*\n\n[Verse 1]\nOn the bank of the river\nStood Running Bear, young Indian brave\nOn the other side of the river\nStood his lovely Indian maid\nLittle White Dove was her name\nSuch a lovely sight to see\nBut their tribes fought with each other\nSo, their love could never be\n\n[Chorus]\nRunning Bear loved Little White Dove\nWith a love big as the sky\nRunning Bear loved Little White Dove\nWith a love that couldn't die\n\n[Verse 2]\nHe couldn't swim the raging river\n'Cause the river was too wide\nHe couldn't reach Little White Dove\nWaiting on the other side\nIn the moonlight he could see her\nThrowing kisses 'cross the waves\nHer little heart was beating faster\nWaiting there for her brave\nYou might also like[Chorus]\nRunning Bear loved Little White Dove\nWith a love big as the sky\nRunning Bear loved Little White Dove\nWith a love that couldn't die\n\n[Verse 3]\nRunning Bear dove in the water\nLittle White Dove did the same\nAnd they swam out to each other\nThrough the swirling stream they came\nAs their hands touched and their lips met\nThe raging river pulled them down\nNow, they'll always be together\nIn that happy huntin' ground\n\n[Chorus]\nRunning Bear loved Little White Dove\nWith a love big as the sky\nRunning Bear loved Little White Dove\nWith a love that couldn't die\n\n[Outro]\n*vocalizations*1Embed"
}