{
 "_type": "song",
 "annotation_count": 5,
 "api_path": "/songs/431519",
 "artist_names": "Faith Hill",
 "full_title": "This Kiss by\u00a0Faith\u00a0Hill",
 "header_image_thumbnail_url": "https://images.genius.com/811e7b635ebcbcc1ec135db421c4fbf7.300x300x1.jpg",
 "header_image_url": "https://images.genius.com/811e7b635ebcbcc1ec135db421c4fbf7.1000x1000x1.jpg",
 "id": 431519,
 "instrumental": false,
 "lyrics_owner_id": 396158,
 "lyrics_state": "complete",
 "lyrics_updated_at": 1661496555,
 "path": "/Faith-hill-this-kiss-lyrics",
 "pyongs_count": 2,
 "relationships_index_url": "https://genius.com/Faith-hill-this-kiss-sample",
 "release_date_components": {
  "year": 1998,
  "month": 3,
  "day": 3
 },
 "release_date_for_display": "March 3, 1998",
 "release_date_with_abbreviated_month_for_display": "Mar. 3, 1998",
 "song_art_image_thumbnail_url": "https://images.genius.com/c3f1435b36fc3f3a532170590d1cdab6.300x300x1.jpg",
 "song_art_image_url": "https://images.genius.com/c3f1435b36fc3f3a532170590d1cdab6.600x600x1.jpg",
 "stats": {
  "unreviewed_annotations": 3,
  "hot": false,
  "pageviews": 23007
 },
 "title": "This Kiss",
 "title_with_featured": "This Kiss",
 "updated_by_human_at": 1692417730,
 "url": "https://genius.com/Faith-hill-this-kiss-lyrics",
 "featured_artists": [],
 "primary_artist": {
  "_type": "artist",
  "api_path": "/artists/48448",
  "header_image_url": "https://images.genius.com/41fef630e8b5c78b62920d4d9b636d65.570x570x1.jpg",
  "id": 48448,
  "image_url": "https://images.genius.com/41fef630e8b5c78b62920d4d9b636d65.570x570x1.jpg",
  "index_character": "f",
  "is_meme_verified": false,
  "is_verified": false,
  "name": "Faith Hill",
  "slug": "Faith-hill",
  "url": "https://genius.com/artists/Faith-hill"
 },
 "artist": "Faith Hill",
 "lyrics": "17 ContributorsThis Kiss Lyrics[Verse 1]\nI don't want another heartbreak\nI don't need another turn to cry, no\nI don't wanna learn the hard way\nBaby, hello\nOh no, goodbye\nBut you got me like a rocket\nShooting straight across the sky\n\n[Chorus]\nIt's the way you love me\nIt's a feeling like this\nIt's centrifugal motion\nIt's perpetual bliss\nIt's that pivotal moment\nIt's, ah, impossible\nThis kiss, this kiss\nUnstoppable\nThis kiss, this kiss\n\n[Verse 2]\nCinderella said to Snow White\n\"How does love get so off course?\nOh, all I wanted was a white knight\nWith a good heart\nSoft touch, fast horse\"\nRide me off into the sunset\nBaby, I'm forever yours\nYou might also like[Chorus]\nIt's the way you love me\nIt's a feeling like this\nIt's centrifugal motion\nIt's perpetual bliss\nIt's that pivotal moment\nIt's, ah, unthinkable\nThis kiss, this kiss\nUnsinkable\nThis kiss, this kiss\n\n[Bridge]\nYou can kiss me in the moonlight\nOn the rooftop under the sky, oh\nYou can kiss me with the windows open\nWhile the rain comes pouring inside, oh\nKiss me in sweet slow motion\nLet's let everything slide\nYou got me floating\nYou got me flying\n\n[Chorus]\nIt's the way you love me (The way)\nIt's a feeling like this\nIt's centrifugal motion (Ahh, ahh)\nIt's perpetual bliss\nIt's that pivotal moment\nIt's, ah, subliminal\nThis kiss, this kiss\nIt's criminal\nThis kiss, this kiss\nIt's the way you love me, baby (The way you love me, baby)\nIt's the way you love me, darling, yeah\n[Chorus]\nIt's the way you love me (The way)\nIt's a feeling like this\nIt's centrifugal motion (Ahh, ahh)\nIt's perpetual bliss\nIt's that pivotal moment\nIt's, ah, subliminal\nThis kiss, this kiss\nIt's criminal\nThis kiss, this kiss\nIt's the way you love me, baby (The way you love me, baby)\nIt's the way you love me darling, yeah\n\n[Outro]\nIt's the way you love me\nIt's a feeling like this\nIt's centrifugal motion2Embed"
}