{
 "_type": "song",
 "annotation_count": 10,
 "api_path": "/songs/107795",
 "artist_names": "Sublime",
 "full_title": "Jailhouse by\u00a0Sublime",
 "header_image_thumbnail_url": "https://images.genius.com/105759f38327ab4010a094f50236eb33.300x273x1.jpg",
 "header_image_url": "https://images.genius.com/105759f38327ab4010a094f50236eb33.600x545x1.jpg",
 "id": 107795,
 "instrumental": false,
 "lyrics_owner_id": 143605,
 "lyrics_state": "complete",
 "lyrics_updated_at": 1656797807,
 "path": "/Sublime-jailhouse-lyrics",
 "pyongs_count": 5,
 "relationships_index_url": "https://genius.com/Sublime-jailhouse-sample",
 "release_date_components": {
  "year": 1996,
  "month": 7,
  "day": 30
 },
 "release_date_for_display": "July 30, 1996",
 "release_date_with_abbreviated_month_for_display": "Jul. 30, 1996",
 "song_art_image_thumbnail_url": "https://images.genius.com/105759f38327ab4010a094f50236eb33.300x273x1.jpg",
 "song_art_image_url": "https://images.genius.com/105759f38327ab4010a094f50236eb33.600x545x1.jpg",
 "stats": {
  "unreviewed_annotations": 1,
  "hot": false,
  "pageviews": 40128
 },
 "title": "Jailhouse",
 "title_with_featured": "Jailhouse",
 "updated_by_human_at": 1656797807,
 "url": "https://genius.com/Sublime-jailhouse-lyrics",
 "featured_artists": [],
 "primary_artist": {
  "_type": "artist",
  "api_path": "/artists/659",
  "header_image_url": "https://images.genius.com/e63b5f899888e46f53fc6e679bd66c8e.183x276x1.jpg",
  "id": 659,
  "image_url": "https://images.genius.com/d61c1469f99333ef183ef8bee4141065.183x183x1.jpg",
  "index_character": "s",
  "is_meme_verified": false,
  "is_verified": false,
  "name": "Sublime",
  "slug": "Sublime",
  "url": "https://genius.com/artists/Sublime"
 },
 "artist": "Sublime",
 "lyrics": "22 ContributorsJailhouse Lyrics[Intro]\nGo!\nAnd I won't give it up to you\nAnd I feel love, feel love, love, love\n\n[Pre-Chorus]\nJailhouse gets empty\nRudy gets plenty\nThe baton stick gets shorter\nRudy gets taller\n\n[Chorus]\n'Em fight against the youth\n'Cause we're strong\nThem are rude, rude people\nCan't fight against the youth\n'Cause we're strong\n'Em are rude, rude people\n\n[Verse 1]\nNow, when I was a youth in 1983\nIt was the best day of my life\nHad the '89 vision, we didn't fuss or no fight\nWhen all the little daughters wanna be my wife\nA vision, it was playin' on my guitar, on my guitar\nI had to be there, I had to be there\nI had to be there, I had to be there\nAnd the rhythm playin'\nI know that I'm gonna be there, yeah\nBud Gaugh will be singing there\nAnd Eric Wilson will be bangin' out there, yeah\nAnd we'll be all singin', with version, with version\nReggae version, version, version, version, oh\nOh!\nYou might also like[Instrumental Break]\n\n[Bridge]\nWhat has been told to the wise and up-rooted? Yeah\nIt's gonna be revealed unto you babes, and Sublime\nRudy, Rudy, Rudy\n\n[Chorus]\nCan't fight against the youth\nRight now, them are rude, rude people\nCan't fight against the resistance\nOh, right now, 'em are rude, rude people\n\n[Bridge 2]\nWe gonna rule this land among children\nWe gonna rule this land\n\n[Verse 2]\n'Cause when that rhythm, it was playin' on my guitar, on my guitar\nI had to be there, I had to be there\nI had to be there, I had to be there\nOh, when I was a youth, it was the best day\nIt was the best day of my life\nWe had the '89 vision, we didn't fuss or no fight\nWhen all the little daughters wanna be my wife\nWhen that rhythm, it was playin on my guitar, on my guitar\nI had to be there, I had to be there\nI had to be there, I had to be there, I had to be there\nHad to be there\n[Instrumental Break]\n\n[Pre-Chorus]\nJailhouse gets empty\nAnd Rudy gets plenty\nBaton stick gets shorter\nRudy gets taller, taller\n\n[Chorus]\n'Em fight against the youth\n'Cause we're strong\nThem are rude, rude people\nCan't fight against the youth5Embed"
}