{
 "_type": "song",
 "annotation_count": 13,
 "api_path": "/songs/349759",
 "artist_names": "My Morning Jacket",
 "full_title": "Circuital by\u00a0My\u00a0Morning Jacket",
 "header_image_thumbnail_url": "https://images.genius.com/e9655f3e51b5a17063897452ae70699c.300x300x1.jpg",
 "header_image_url": "https://images.genius.com/e9655f3e51b5a17063897452ae70699c.608x608x1.jpg",
 "id": 349759,
 "instrumental": false,
 "lyrics_owner_id": 396303,
 "lyrics_state": "complete",
 "lyrics_updated_at": 1598456841,
 "path": "/My-morning-jacket-circuital-lyrics",
 "pyongs_count": 1,
 "relationships_index_url": "https://genius.com/My-morning-jacket-circuital-sample",
 "release_date_components": {
  "year": 2011,
  "month": 5,
  "day": 31
 },
 "release_date_for_display": "May 31, 2011",
 "release_date_with_abbreviated_month_for_display": "May. 31, 2011",
 "song_art_image_thumbnail_url": "https://images.genius.com/e9655f3e51b5a17063897452ae70699c.300x300x1.jpg",
 "song_art_image_url": "https://images.genius.com/e9655f3e51b5a17063897452ae70699c.608x608x1.jpg",
 "stats": {
  "unreviewed_annotations": 2,
  "hot": false,
  "pageviews": 10055
 },
 "title": "Circuital",
 "title_with_featured": "Circuital",
 "updated_by_human_at": 1598456839,
 "url": "https://genius.com/My-morning-jacket-circuital-lyrics",
 "featured_artists": [],
 "primary_artist": {
  "_type": "artist",
  "api_path": "/artists/60652",
  "header_image_url": "https://images.genius.com/4a35b49eab34413eaba345dd6819bec5.1000x641x1.jpg",
  "id": 60652,
  "image_url": "https://images.genius.com/c791c43e36dd633c8a05fbf2199717bd.1000x1000x1.jpg",
  "index_character": "m",
  "is_meme_verified": false,
  "is_verified": true,
  "name": "My Morning Jacket",
  "slug": "My-morning-jacket",
  "url": "https://genius.com/artists/My-morning-jacket",
  "iq": 100
 },
 "artist": "My Morning Jacket",
 "lyrics": "13 ContributorsCircuital LyricsSpinning out gracefully\nGoing nowhere quickly\nI am older day by day\nStill going back to my childhood way\nCircuital\nRound and round patiently\nGetting lost by the guide\nAnd I'm all worked up over nothing\nCircuits\nAll running out\nConnect my body\nDeep into the ground\nCircuits\nConnect the Earth to the moon\nAnd link our heavenly bodies\nNot a moment too soon\nWell you can fling open the windows\nOr you can board 'em up\nSatan's jeweled crown\nOr Christ\u2019s humble cup\nYou think you'll find yourself out there\nOut in the lion\u2019s den\nIn some bloody battle\nOver belief systems\nYou might also likeOr disappear into the vacuum\nTotal neutrality\nWhere you can't lose nothing\nBut nothing can be gained\nWell anyway you cut it\nWe're just spinning around\nOut on the circuit\nOver the hallowed ground\nOut on the circuit\nOver the hallowed ground\nEnding up in the same place\nThat we started out\nRight back in the same place\nRight back in the same place\nThat we started out1Embed"
}