{
 "_type": "song",
 "annotation_count": 10,
 "api_path": "/songs/1092284",
 "artist_names": "Don Henley",
 "full_title": "Sunset Grill by\u00a0Don\u00a0Henley",
 "header_image_thumbnail_url": "https://images.genius.com/4faf4816dbd09255e88c5c685701b066.300x300x1.jpg",
 "header_image_url": "https://images.genius.com/4faf4816dbd09255e88c5c685701b066.1000x1000x1.jpg",
 "id": 1092284,
 "instrumental": false,
 "lyrics_owner_id": 2189879,
 "lyrics_state": "complete",
 "lyrics_updated_at": 1681672673,
 "path": "/Don-henley-sunset-grill-lyrics",
 "pyongs_count": 1,
 "relationships_index_url": "https://genius.com/Don-henley-sunset-grill-sample",
 "release_date_components": {
  "year": 1984,
  "month": 11,
  "day": 19
 },
 "release_date_for_display": "November 19, 1984",
 "release_date_with_abbreviated_month_for_display": "Nov. 19, 1984",
 "song_art_image_thumbnail_url": "https://images.genius.com/4faf4816dbd09255e88c5c685701b066.300x300x1.jpg",
 "song_art_image_url": "https://images.genius.com/4faf4816dbd09255e88c5c685701b066.1000x1000x1.jpg",
 "stats": {
  "unreviewed_annotations": 9,
  "hot": false,
  "pageviews": 33954
 },
 "title": "Sunset Grill",
 "title_with_featured": "Sunset Grill",
 "updated_by_human_at": 1681672673,
 "url": "https://genius.com/Don-henley-sunset-grill-lyrics",
 "featured_artists": [],
 "primary_artist": {
  "_type": "artist",
  "api_path": "/artists/41201",
  "header_image_url": "https://images.genius.com/828c16c902bd4090f8c8f7313e4596ce.556x415x1.jpg",
  "id": 41201,
  "image_url": "https://images.genius.com/f5b67a4f2c13dd8926dea2f4cd74f9e9.649x649x1.png",
  "index_character": "d",
  "is_meme_verified": false,
  "is_verified": false,
  "name": "Don Henley",
  "slug": "Don-henley",
  "url": "https://genius.com/artists/Don-henley"
 },
 "artist": "Don Henley",
 "lyrics": "9 ContributorsSunset Grill Lyrics[Verse 1]\nLet's go down to the Sunset Grill\nWe can watch the working girls go by\nWatch the basket people walk around and mumble\nStare out at the auburn sky\n\n[Pre-Chorus 1]\nThere's an old man there from the old world\nTo him, it's all the same\nCalls all his customers by name\n\n[Chorus]\nDown at the Sunset Grill\nDown at the Sunset Grill\nDown at the Sunset Grill\nDown at the Sunset Grill\n\n[Verse 2]\nYou see a lot more meanness in the city\nIt's the kind that eats you up inside\nHard to come away with anything that feels like dignity\nHard to get home with any pride\n\n[Pre-Chorus 2]\nThese days a man makes you somethin'\nAnd you never see his face\nBut there is no hiding place\nYou might also like[Chorus]\nDown at the Sunset Grill\nDown at the Sunset Grill\nDown at the Sunset Grill\nDown at the Sunset Grill\n\n[Bridge]\nRespectable little murders pay\nThey get more respectable every day\nDon't worry, girl\nI'm gonna stick by you\nAnd someday soon\nWe're gonna get in that car\nAnd get outta here\n\n[Solo]\n\n[Verse 1 (reprise)]\nLet's go down to the Sunset Grill\nWatch the working girls go by\nWatch the basket people walk around and mumble\nGaze out at the auburn sky\n\n[Pre-Chorus 3]\nMaybe we'll leave come springtime\nMeanwhile, have another beer\nWhat would we do without all these jerks anyway?\nBesides, all our friends are here\n[Chorus]\nDown at the Sunset Grill\nDown at the Sunset Grill\nDown at the Sunset Grill\nDown at the Sunset Grill\n\n[Instrumental Outro]1Embed"
}